ECP/MADES_SOAP_API.py
ECP/__init__.py
ECP/_version.py
ecp_api-0.0.7.dist-info/LICENSE
ecp_api-0.0.7.dist-info/METADATA
ecp_api-0.0.7.dist-info/WHEEL
ecp_api-0.0.7.dist-info/top_level.txt
ecp_api-0.0.7.dist-info/RECORD
