Metadata-Version: 2.1
Name: ecp-api
Version: 0.0.7
Summary: ENTSO-E ECP software MADES SOAP API implementation in python
Home-page: https://github.com/Haigutus/ECP
Author: Kristjan Vilgo
Author-email: kristjan.vilgo@gmail.com
License: GPL2
Platform: UNKNOWN
Classifier: Programming Language :: Python :: 3
Classifier: License :: OSI Approved :: GNU General Public License v2 (GPLv2)
Classifier: Operating System :: OS Independent
Requires-Dist: requests
Requires-Dist: zeep
Requires-Dist: urllib3
Requires-Dist: lxml
